libxmp/__init__.py
libxmp/consts.py
libxmp/core.py
libxmp/exempi.py
libxmp/files.py
libxmp/utils.py
libxmp/version.py
python_xmp_toolkit-2.0.1.dist-info/AUTHORS
python_xmp_toolkit-2.0.1.dist-info/LICENSE
python_xmp_toolkit-2.0.1.dist-info/METADATA
python_xmp_toolkit-2.0.1.dist-info/WHEEL
python_xmp_toolkit-2.0.1.dist-info/top_level.txt
python_xmp_toolkit-2.0.1.dist-info/RECORD
