Metadata-Version: 2.1
Name: python-xmp-toolkit
Version: 2.0.1
Summary: Python XMP Toolkit for working with metadata.
Home-page: https://github.com/python-xmp-toolkit/python-xmp-toolkit
Download-URL: https://pypi.python.org/pypi/python-xmp-toolkit
Author: Lars Holm Nielsen, John Evans, Federico Caboni & Amit Kapadia
Author-email: lars@hankat.dk
License: New BSD License
Classifier: Development Status :: 5 - Production/Stable
Classifier: Intended Audience :: Developers
Classifier: License :: OSI Approved :: BSD License
Classifier: Operating System :: MacOS :: MacOS X
Classifier: Operating System :: POSIX :: Linux
Classifier: Programming Language :: Python
Classifier: Programming Language :: Python :: 2
Classifier: Programming Language :: Python :: 3
Classifier: Topic :: Multimedia
Classifier: Topic :: Software Development :: Libraries
Classifier: Topic :: Utilities
License-File: LICENSE
License-File: AUTHORS
Requires-Dist: pytz
